MahjongPyWrapper.cp39-win_amd64.pyd
pymahjong/__init__.py
pymahjong/base_modules.py
pymahjong/env_pymahjong.py
pymahjong/models.py
pymahjong/tenhou_paipu_check.py
pymahjong/test.py
pymahjong-1.0.4.dist-info/METADATA
pymahjong-1.0.4.dist-info/WHEEL
pymahjong-1.0.4.dist-info/top_level.txt
pymahjong-1.0.4.dist-info/RECORD
